odoo/addons/website_no_crawler/README.rst
odoo/addons/website_no_crawler/__init__.py
odoo/addons/website_no_crawler/__manifest__.py
odoo/addons/website_no_crawler/controllers/__init__.py
odoo/addons/website_no_crawler/controllers/main.py
odoo/addons/website_no_crawler/data/data.xml
odoo/addons/website_no_crawler/i18n/ca.po
odoo/addons/website_no_crawler/i18n/es.po
odoo/addons/website_no_crawler/i18n/hr.po
odoo/addons/website_no_crawler/i18n/it.po
odoo/addons/website_no_crawler/i18n/nl.po
odoo/addons/website_no_crawler/i18n/website_no_crawler.pot
odoo/addons/website_no_crawler/readme/CONFIGURE.rst
odoo/addons/website_no_crawler/readme/CONTRIBUTORS.rst
odoo/addons/website_no_crawler/readme/DESCRIPTION.rst
odoo/addons/website_no_crawler/readme/USAGE.rst
odoo/addons/website_no_crawler/static/description/icon.png
odoo/addons/website_no_crawler/static/description/index.html
odoo/addons/website_no_crawler/views/disable_robots.xml
odoo14_addon_website_no_crawler-14.0.1.2.0.dist-info/METADATA
odoo14_addon_website_no_crawler-14.0.1.2.0.dist-info/WHEEL
odoo14_addon_website_no_crawler-14.0.1.2.0.dist-info/top_level.txt
odoo14_addon_website_no_crawler-14.0.1.2.0.dist-info/RECORD
